cn2en/__init__.py
cn2en/input_lang.pkl
cn2en/model.pth
cn2en/model.py
cn2en/output_lang.pkl
cn2en-0.0.118.dist-info/LICENSE
cn2en-0.0.118.dist-info/METADATA
cn2en-0.0.118.dist-info/WHEEL
cn2en-0.0.118.dist-info/top_level.txt
cn2en-0.0.118.dist-info/RECORD
